{
  "templates": {
    "type": "JSON",
    "content": [
      {
        "id": "144241613",
        "Flight": "WS2773",
        "PickupDate": "2025-08-16",
        "PickupTime": "05:55",
        "HotelName": "Family Club at Grand Riviera Princess",
        "HotelNumber": 3422
      },
      {
        "id": "144494253",
        "Flight": "WS2963",
        "PickupDate": "2025-08-16",
        "PickupTime": "07:05",
        "HotelName": "Family Club at Grand Riviera Princess",
        "HotelNumber": 3422
      },
      {
        "id": "145103823",
        "Flight": "WS2963",
        "PickupDate": "2025-08-16",
        "PickupTime": "06:55",
        "HotelName": "Platinum Yucatán Princess ",
        "HotelNumber": 3614
      },
      {
        "id": "TCOCH-26178270",
        "Flight": "H25554",
        "PickupDate": "2025-08-16",
        "PickupTime": "12:40",
        "HotelName": "Platinum Yucatán Princess ",
        "HotelNumber": 3614
      },
      {
        "id": "145043353",
        "Flight": "WS2773",
        "PickupDate": "2025-08-16",
        "PickupTime": "05:45",
        "HotelName": "Platinum Yucatán Princess ",
        "HotelNumber": 3614
      },
      {
        "id": "144400873",
        "Flight": "WS2773",
        "PickupDate": "2025-08-16",
        "PickupTime": "06:05",
        "HotelName": "Grand Sunset Princess",
        "HotelNumber": 3470
      }
    ],
    "source": {
      "data_source": "Google Sheets (Private)",
      "update_frequency": "Automated"
    }
  }
}